hmeqotools/__init__.py
hmeqotools/ipinfo.py
hmeqotools/py.typed
hmeqotools/randhex.py
hmeqotools/versioninfo.py
hmeqotools/crypto/__init__.py
hmeqotools/crypto/aes.py
hmeqotools/crypto/dh.py
hmeqotools/crypto/padding.py
hmeqotools/crypto/rsa.py
hmeqotools/interesting/__init__.py
hmeqotools/interesting/inspectcodechange.py
hmeqotools/mathutil/__init__.py
hmeqotools/mathutil/calculator.py
hmeqotools/mathutil/dec.py
hmeqotools/mathutil/formula.py
hmeqotools/mathutil/funcs.py
hmeqotools/mathutil/predict.py
hmeqotools/mathutil/repattern.py
hmeqotools/mathutil/vectorut.py
hmeqotools/mathutil/algorithm/__init__.py
hmeqotools/mathutil/algorithm/search.py
hmeqotools/mathutil/algorithm/sort.py
hmeqotools/scripts/__init__.py
hmeqotools/scripts/cleancache.py
hmeqotools/stdutil/__init__.py
hmeqotools/stdutil/ctypesutil.py
hmeqotools/stdutil/osutil.py
hmeqotools/stdutil/tkinterutil.py
hmeqotools/stdutil/winregutil.py
hmeqotools/stdutil/threadingutil/__init__.py
hmeqotools/stdutil/threadingutil/asynctask.py
hmeqotools/stdutil/threadingutil/locking.py
hmeqotools/stdutil/threadingutil/taskrunner.py
hmeqotools-0.1.4.dist-info/METADATA
hmeqotools-0.1.4.dist-info/WHEEL
hmeqotools-0.1.4.dist-info/licenses/LICENSE
hmeqotools-0.1.4.dist-info/RECORD
