Metadata-Version: 2.4
Name: hmeqotools
Version: 0.1.4
Summary: hmeqo's toolkit for Python.
License: MIT License
License-File: LICENSE
Requires-Python: >=3.8
Requires-Dist: httpx
